src/__init__.py
src/app.py
src/transcribe_tools.py
src/transcribe_ui.py
arbi_tr_frontend-0.1.1.dist-info/METADATA
arbi_tr_frontend-0.1.1.dist-info/WHEEL
arbi_tr_frontend-0.1.1.dist-info/entry_points.txt
arbi_tr_frontend-0.1.1.dist-info/RECORD
