Metadata-Version: 2.1
Name: arbi-tr-frontend
Version: 0.1.1
Summary: 
License: MIT
Author: Dmitri Evseev
Author-email: dmitri.evseev@arbi.city
Requires-Python: >=3.11,<4.0
Classifier: License :: OSI Approved :: MIT License
Classifier: Programming Language :: Python :: 3
Classifier: Programming Language :: Python :: 3.11
Classifier: Programming Language :: Python :: 3.12
Requires-Dist: pandas (>=2.2.1,<3.0.0)
Requires-Dist: requests (>=2.31.0,<3.0.0)
Requires-Dist: streamlit (>=1.31.1,<2.0.0)
Requires-Dist: yt-dlp (>=2024.4.9,<2025.0.0)
